odoo/addons/stock_picking_operation_quick_change/README.rst
odoo/addons/stock_picking_operation_quick_change/__init__.py
odoo/addons/stock_picking_operation_quick_change/__manifest__.py
odoo/addons/stock_picking_operation_quick_change/i18n/de.po
odoo/addons/stock_picking_operation_quick_change/i18n/es.po
odoo/addons/stock_picking_operation_quick_change/i18n/fr.po
odoo/addons/stock_picking_operation_quick_change/i18n/it.po
odoo/addons/stock_picking_operation_quick_change/i18n/pt_BR.po
odoo/addons/stock_picking_operation_quick_change/i18n/sl.po
odoo/addons/stock_picking_operation_quick_change/i18n/stock_picking_operation_quick_change.pot
odoo/addons/stock_picking_operation_quick_change/readme/CONTRIBUTORS.md
odoo/addons/stock_picking_operation_quick_change/readme/DESCRIPTION.md
odoo/addons/stock_picking_operation_quick_change/readme/USAGE.md
odoo/addons/stock_picking_operation_quick_change/security/ir.model.access.csv
odoo/addons/stock_picking_operation_quick_change/static/description/icon.png
odoo/addons/stock_picking_operation_quick_change/static/description/icon.svg
odoo/addons/stock_picking_operation_quick_change/static/description/index.html
odoo/addons/stock_picking_operation_quick_change/tests/__init__.py
odoo/addons/stock_picking_operation_quick_change/tests/test_stock_picking_operation_quick_change.py
odoo/addons/stock_picking_operation_quick_change/views/stock_picking_view.xml
odoo/addons/stock_picking_operation_quick_change/wizards/__init__.py
odoo/addons/stock_picking_operation_quick_change/wizards/stock_picking_wizard.py
odoo/addons/stock_picking_operation_quick_change/wizards/stock_picking_wizard_view.xml
odoo_addon_stock_picking_operation_quick_change-18.0.1.0.0.2.dist-info/METADATA
odoo_addon_stock_picking_operation_quick_change-18.0.1.0.0.2.dist-info/WHEEL
odoo_addon_stock_picking_operation_quick_change-18.0.1.0.0.2.dist-info/top_level.txt
odoo_addon_stock_picking_operation_quick_change-18.0.1.0.0.2.dist-info/RECORD
